{
    "Laboratory": {
        "south": "Office",
        "item": "Beam-O-Mat"
    },
    "Office": {
        "north": "Laboratory",
        "south": "Hall"
    },
    "Hall": {
        "north": "Office",
        "east": "Library",
        "south": "Kitchen"
    },
    "Kitchen": {
        "north": "Hall",
        "east": "Dining Room",
        "item": "bottle of olive oil"
    },
    "Library": {
        "south": "Dining Room",
        "west": "Hall",
        "item": "BookOfLife"
    },
    "Dining Room": {
        "north": "Library",
        "south": "Garden",
        "west": "Kitchen",
        "item": "potion"
    },
    "Garden": {
        "north": "Dining Room",
        "south": "Shag"
    },
    "Shag": {
        "north": "Garden",
        "item": "chainsaw"
    }
}